pmentropy/Node.py
pmentropy/__init__.py
pmentropy/entropy.py
pmentropy/file.py
pmentropy/kNearestLevenshtein.py
pmentropy/tools.py
pmentropy/entropys/__init__.py
pmentropy/entropys/globalBlockEntropy.py
pmentropy/entropys/kBlockEntropy.py
pmentropy/entropys/kBlockEntropyRate.py
pmentropy/entropys/kLEntropy.py
pmentropy/entropys/kNNEntropy.py
pmentropy/entropys/lempelZivEntropyRate.py
pmentropy/entropys/prefixEntropy.py
pmentropy/entropys/traceEntropy.py
pmentropy/entropys/uniqueTrace.py
pmentropy-0.0.5.dist-info/LICENSE
pmentropy-0.0.5.dist-info/METADATA
pmentropy-0.0.5.dist-info/WHEEL
pmentropy-0.0.5.dist-info/top_level.txt
pmentropy-0.0.5.dist-info/RECORD
