Metadata-Version: 2.1
Name: pmentropy
Version: 0.0.5
Summary: Compute in python entropy for process mining describe in Back, C.O., Debois, S. & Slaats, T. Entropy as a Measure of Log Variability. J Data Semant 8, 129–156 (2019). https://doi.org/10.1007/s13740-019-00105-3 (https://rdcu.be/dJMwH)
Home-page: https://github.com/TavTanguy/pmentropy
Author: Taverna Tanguy
Author-email: taverna.tanguy@gmail.com
License: GNU General Public License v3
Classifier: Intended Audience :: Developers
Classifier: License :: OSI Approved :: GNU General Public License v3 (GPLv3)
Classifier: Programming Language :: Python :: 3.11
License-File: LICENSE
Requires-Dist: numpy >=1.26.4
Requires-Dist: pm4py >=2.7.11.10
Requires-Dist: Levenshtein >=0.25.1
